terminal/404.html
terminal/__init__.py
terminal/base.html
terminal/main.html
terminal/mkdocs_theme.yml
terminal/theme_version.html
terminal/css/normalize.css
terminal/css/terminal.css
terminal/css/theme.css
terminal/css/theme.footer.css
terminal/css/theme.tile_grid.css
terminal/css/fontawesome/css/fontawesome.css
terminal/css/fontawesome/css/fontawesome.min.css
terminal/css/fontawesome/css/solid.css
terminal/css/fontawesome/css/solid.min.css
terminal/css/fontawesome/webfonts/fa-solid-900.ttf
terminal/css/fontawesome/webfonts/fa-solid-900.woff2
terminal/css/palettes/blueberry.css
terminal/css/palettes/dark.css
terminal/css/palettes/default.css
terminal/css/palettes/gruvbox_dark.css
terminal/css/palettes/lightyear.css
terminal/css/palettes/pink.css
terminal/css/palettes/red_drum.css
terminal/css/palettes/sans.css
terminal/css/palettes/sans_dark.css
terminal/css/search/bootstrap-modal.css
terminal/js/bootstrap/bootstrap.js
terminal/js/bootstrap/bootstrap.js.map
terminal/js/bootstrap/bootstrap.min.js
terminal/js/bootstrap/bootstrap.min.js.map
terminal/js/jquery/jquery-1.10.1.min.js
terminal/js/jquery/jquery-1.10.1.min.js.map
terminal/js/mkdocs/LICENSE
terminal/js/mkdocs/base.js
terminal/legal/legal.md
terminal/macros/prev-next.j2
terminal/macros/toc.j2
terminal/macros/side-nav/section-index-page-title.j2
terminal/macros/side-nav/side-nav-item-class.j2
terminal/macros/side-nav/side-nav-item.j2
terminal/macros/top-nav/search-button.j2
terminal/partials/favicon.html
terminal/partials/footer.html
terminal/partials/html-title.html
terminal/partials/page-base.html
terminal/partials/page.html
terminal/partials/styles.html
terminal/partials/page-content/after-content.html
terminal/partials/page-content/before-content.html
terminal/partials/page-content/content.html
terminal/partials/page-content/revision.html
terminal/partials/search/modal.html
terminal/partials/search/scripts.html
terminal/partials/search/mkdocs/LICENSE
terminal/partials/search/mkdocs/search-modal.html
mkdocs_terminal-4.8.0.dist-info/METADATA
mkdocs_terminal-4.8.0.dist-info/WHEEL
mkdocs_terminal-4.8.0.dist-info/entry_points.txt
mkdocs_terminal-4.8.0.dist-info/licenses/LICENSE
mkdocs_terminal-4.8.0.dist-info/RECORD
