Metadata-Version: 2.4
Name: mkdocs-terminal
Version: 4.8.0
Summary: Terminal.css theme for MkDocs
Project-URL: Source, https://github.com/ntno/mkdocs-terminal
Project-URL: Issues, https://github.com/ntno/mkdocs-terminal/issues
Project-URL: Documentation, https://ntno.github.io/mkdocs-terminal
Author: Natan Organick
License-Expression: MIT
License-File: LICENSE
Keywords: documentation,mkdocs,theme
Classifier: Development Status :: 4 - Beta
Classifier: Environment :: Web Environment
Classifier: License :: OSI Approved :: MIT License
Classifier: Programming Language :: Python
Classifier: Topic :: Documentation
Classifier: Topic :: Software Development :: Documentation
Classifier: Topic :: Text Processing :: Markup :: HTML
Requires-Python: >=3.7
Requires-Dist: jinja2>=2.10
Requires-Dist: markdown
Requires-Dist: mkdocs>=1.4.2
Requires-Dist: pygments
Requires-Dist: pymdown-extensions
